{
  "/App.js": {
    "code": "export default function App() {\r\n  return <h1>Project 10-5</h1>;\r\n}\r\n",
    "hidden": false
  },
  "/index.html": {
    "code": "<div id=\"root\"></div>\r\n",
    "hidden": true
  },
  "/index.js": {
    "code": "import { createRoot } from \"react-dom/client\";\r\nimport App from \"./App.js\";\r\n\r\ncreateRoot(document.getElementById(\"root\")).render(<App />);\r\n",
    "hidden": true
  },
  "/package.json": {
    "code": "{\n  \"name\": \"code10_5\",\n  \"version\": \"1.0.0\",\n  \"main\": \"/index.js\",\n  \"dependencies\": {\n    \"react\": \"19.0.0\",\n    \"react-dom\": \"19.0.0\"\n  }\n}",
    "hidden": true
  }
}
